{
  "metadata": {
    "タイトル": "MC応急処置サンプル_1744618789490.pptx",
    "作成者": "保守用車システム",
    "作成日": "2025-04-14T08:20:03.495Z",
    "修正日": "2025-04-14T08:20:03.495Z",
    "説明": "保守用車マニュアル情報"
  },
  "slides": [
    {
      "スライド番号": 1,
      "タイトル": "保守用車緊急対応マニュアル",
      "本文": [
        "保守用車のトラブルシューティングと緊急時対応手順"
      ],
      "ノート": "スライド 1のノート: 保守用車緊急対応マニュアル\n保守用車のトラブルシューティングと緊急時対応手順",
      "画像テキスト": [
        {
          "画像パス": "/uploads/images/mc_1744618803268_001.png",
          "テキスト": "保守用車のトラブルシューティングと緊急時対応手順"
        }
      ]
    },
    {
      "スライド番号": 2,
      "タイトル": "エンジン関連の緊急対応",
      "本文": [
        "エンジン停止時の診断と応急処置の手順"
      ],
      "ノート": "スライド 2のノート: エンジン関連の緊急対応\nエンジン停止時の診断と応急処置の手順",
      "画像テキスト": [
        {
          "画像パス": "/uploads/images/mc_1744618803268_002.png",
          "テキスト": "エンジン停止時の診断と応急処置の手順"
        }
      ]
    },
    {
      "スライド番号": 3,
      "タイトル": "運転キャビンの緊急措置",
      "本文": [
        "運転キャビンの問題発生時の対応フロー"
      ],
      "ノート": "スライド 3のノート: 運転キャビンの緊急措置\n運転キャビンの問題発生時の対応フロー",
      "画像テキスト": [
        {
          "画像パス": "/uploads/images/mc_1744618803268_003.png",
          "テキスト": "運転キャビンの問題発生時の対応フロー"
        }
      ]
    },
    {
      "スライド番号": 4,
      "タイトル": "フレーム構造と安全確認",
      "本文": [
        "フレーム損傷時の安全確認と応急対応"
      ],
      "ノート": "スライド 4のノート: フレーム構造と安全確認\nフレーム損傷時の安全確認と応急対応",
      "画像テキスト": [
        {
          "画像パス": "/uploads/images/mc_1744618803268_004.png",
          "テキスト": "フレーム損傷時の安全確認と応急対応"
        }
      ]
    }
  ],
  "embeddedImages": [
    {
      "元のファイル名": "ppt/media/image1.jpeg",
      "抽出パス": "/uploads/images/mc_1744618803268_img_001.png",
      "保存日時": "2025-04-14T08:20:03.319Z",
      "サイズ": 123085,
      "形式": "PNG"
    },
    {
      "元のファイル名": "ppt/media/image2.jpeg",
      "抽出パス": "/uploads/images/mc_1744618803268_img_002.png",
      "保存日時": "2025-04-14T08:20:03.320Z",
      "サイズ": 115194,
      "形式": "PNG"
    },
    {
      "元のファイル名": "ppt/media/image3.jpeg",
      "抽出パス": "/uploads/images/mc_1744618803268_img_003.png",
      "保存日時": "2025-04-14T08:20:03.320Z",
      "サイズ": 96309,
      "形式": "PNG"
    },
    {
      "元のファイル名": "ppt/media/image4.png",
      "抽出パス": "/uploads/images/mc_1744618803268_img_004.png",
      "保存日時": "2025-04-14T08:20:03.320Z",
      "サイズ": 2897,
      "形式": "PNG"
    },
    {
      "元のファイル名": "ppt/media/image5.png",
      "抽出パス": "/uploads/images/mc_1744618803268_img_005.png",
      "保存日時": "2025-04-14T08:20:03.321Z",
      "サイズ": 25651,
      "形式": "PNG"
    },
    {
      "元のファイル名": "ppt/media/image6.png",
      "抽出パス": "/uploads/images/mc_1744618803268_img_006.png",
      "保存日時": "2025-04-14T08:20:03.321Z",
      "サイズ": 84031,
      "形式": "PNG"
    },
    {
      "元のファイル名": "ppt/media/image7.jpeg",
      "抽出パス": "/uploads/images/mc_1744618803268_img_007.png",
      "保存日時": "2025-04-14T08:20:03.333Z",
      "サイズ": 3254152,
      "形式": "PNG"
    },
    {
      "元のファイル名": "ppt/media/image8.jpeg",
      "抽出パス": "/uploads/images/mc_1744618803268_img_008.png",
      "保存日時": "2025-04-14T08:20:03.342Z",
      "サイズ": 2695982,
      "形式": "PNG"
    },
    {
      "元のファイル名": "ppt/media/image9.jpeg",
      "抽出パス": "/uploads/images/mc_1744618803268_img_009.png",
      "保存日時": "2025-04-14T08:20:03.343Z",
      "サイズ": 47393,
      "形式": "PNG"
    },
    {
      "元のファイル名": "ppt/media/image10.jpeg",
      "抽出パス": "/uploads/images/mc_1744618803268_img_010.png",
      "保存日時": "2025-04-14T08:20:03.349Z",
      "サイズ": 1846529,
      "形式": "PNG"
    },
    {
      "元のファイル名": "ppt/media/image11.jpeg",
      "抽出パス": "/uploads/images/mc_1744618803268_img_011.png",
      "保存日時": "2025-04-14T08:20:03.358Z",
      "サイズ": 2508320,
      "形式": "PNG"
    },
    {
      "元のファイル名": "ppt/media/image12.jpeg",
      "抽出パス": "/uploads/images/mc_1744618803268_img_012.png",
      "保存日時": "2025-04-14T08:20:03.366Z",
      "サイズ": 2508192,
      "形式": "PNG"
    },
    {
      "元のファイル名": "ppt/media/image13.jpeg",
      "抽出パス": "/uploads/images/mc_1744618803268_img_013.png",
      "保存日時": "2025-04-14T08:20:03.366Z",
      "サイズ": 34148,
      "形式": "PNG"
    },
    {
      "元のファイル名": "ppt/media/image14.jpeg",
      "抽出パス": "/uploads/images/mc_1744618803268_img_014.png",
      "保存日時": "2025-04-14T08:20:03.366Z",
      "サイズ": 23721,
      "形式": "PNG"
    },
    {
      "元のファイル名": "ppt/media/image15.png",
      "抽出パス": "/uploads/images/mc_1744618803268_img_015.png",
      "保存日時": "2025-04-14T08:20:03.367Z",
      "サイズ": 26216,
      "形式": "PNG"
    },
    {
      "元のファイル名": "ppt/media/image16.png",
      "抽出パス": "/uploads/images/mc_1744618803268_img_016.png",
      "保存日時": "2025-04-14T08:20:03.367Z",
      "サイズ": 4040,
      "形式": "PNG"
    },
    {
      "元のファイル名": "ppt/media/image17.png",
      "抽出パス": "/uploads/images/mc_1744618803268_img_017.png",
      "保存日時": "2025-04-14T08:20:03.367Z",
      "サイズ": 4970,
      "形式": "PNG"
    },
    {
      "元のファイル名": "ppt/media/image18.png",
      "抽出パス": "/uploads/images/mc_1744618803268_img_018.png",
      "保存日時": "2025-04-14T08:20:03.367Z",
      "サイズ": 3164,
      "形式": "PNG"
    },
    {
      "元のファイル名": "ppt/media/image19.png",
      "抽出パス": "/uploads/images/mc_1744618803268_img_019.png",
      "保存日時": "2025-04-14T08:20:03.367Z",
      "サイズ": 3992,
      "形式": "PNG"
    },
    {
      "元のファイル名": "ppt/media/image20.png",
      "抽出パス": "/uploads/images/mc_1744618803268_img_020.png",
      "保存日時": "2025-04-14T08:20:03.368Z",
      "サイズ": 2001,
      "形式": "PNG"
    },
    {
      "元のファイル名": "ppt/media/image21.jpeg",
      "抽出パス": "/uploads/images/mc_1744618803268_img_021.png",
      "保存日時": "2025-04-14T08:20:03.377Z",
      "サイズ": 2792050,
      "形式": "PNG"
    },
    {
      "元のファイル名": "ppt/media/image22.JPG",
      "抽出パス": "/uploads/images/mc_1744618803268_img_022.png",
      "保存日時": "2025-04-14T08:20:03.392Z",
      "サイズ": 3006477,
      "形式": "PNG"
    },
    {
      "元のファイル名": "ppt/media/image23.jpeg",
      "抽出パス": "/uploads/images/mc_1744618803268_img_023.png",
      "保存日時": "2025-04-14T08:20:03.399Z",
      "サイズ": 1990502,
      "形式": "PNG"
    },
    {
      "元のファイル名": "ppt/media/image24.png",
      "抽出パス": "/uploads/images/mc_1744618803268_img_024.png",
      "保存日時": "2025-04-14T08:20:03.400Z",
      "サイズ": 284214,
      "形式": "PNG"
    },
    {
      "元のファイル名": "ppt/media/image25.jpeg",
      "抽出パス": "/uploads/images/mc_1744618803268_img_025.png",
      "保存日時": "2025-04-14T08:20:03.400Z",
      "サイズ": 25920,
      "形式": "PNG"
    },
    {
      "元のファイル名": "ppt/media/image26.png",
      "抽出パス": "/uploads/images/mc_1744618803268_img_026.png",
      "保存日時": "2025-04-14T08:20:03.401Z",
      "サイズ": 19272,
      "形式": "PNG"
    },
    {
      "元のファイル名": "ppt/media/image27.jpeg",
      "抽出パス": "/uploads/images/mc_1744618803268_img_027.png",
      "保存日時": "2025-04-14T08:20:03.401Z",
      "サイズ": 50449,
      "形式": "PNG"
    },
    {
      "元のファイル名": "ppt/media/image28.JPG",
      "抽出パス": "/uploads/images/mc_1744618803268_img_028.png",
      "保存日時": "2025-04-14T08:20:03.412Z",
      "サイズ": 3260242,
      "形式": "PNG"
    },
    {
      "元のファイル名": "ppt/media/image29.jpeg",
      "抽出パス": "/uploads/images/mc_1744618803268_img_029.png",
      "保存日時": "2025-04-14T08:20:03.412Z",
      "サイズ": 17990,
      "形式": "PNG"
    },
    {
      "元のファイル名": "ppt/media/image30.png",
      "抽出パス": "/uploads/images/mc_1744618803268_img_030.png",
      "保存日時": "2025-04-14T08:20:03.428Z",
      "サイズ": 4679974,
      "形式": "PNG"
    },
    {
      "元のファイル名": "ppt/media/image31.png",
      "抽出パス": "/uploads/images/mc_1744618803268_img_031.png",
      "保存日時": "2025-04-14T08:20:03.485Z",
      "サイズ": 16815454,
      "形式": "PNG"
    },
    {
      "元のファイル名": "ppt/media/image32.png",
      "抽出パス": "/uploads/images/mc_1744618803268_img_032.png",
      "保存日時": "2025-04-14T08:20:03.495Z",
      "サイズ": 2801867,
      "形式": "PNG"
    }
  ],
  "textContent": "\nスライド 1: 保守用車緊急対応マニュアル\n保守用車のトラブルシューティングと緊急時対応手順\n\n\nスライド 2: エンジン関連の緊急対応\nエンジン停止時の診断と応急処置の手順\n\n\nスライド 3: 運転キャビンの緊急措置\n運転キャビンの問題発生時の対応フロー\n\n\nスライド 4: フレーム構造と安全確認\nフレーム損傷時の安全確認と応急対応\n\n\n抽出された埋め込み画像 (32個):\n画像 1: /uploads/images/mc_1744618803268_img_001.png\n画像 2: /uploads/images/mc_1744618803268_img_002.png\n画像 3: /uploads/images/mc_1744618803268_img_003.png\n画像 4: /uploads/images/mc_1744618803268_img_004.png\n画像 5: /uploads/images/mc_1744618803268_img_005.png\n画像 6: /uploads/images/mc_1744618803268_img_006.png\n画像 7: /uploads/images/mc_1744618803268_img_007.png\n画像 8: /uploads/images/mc_1744618803268_img_008.png\n画像 9: /uploads/images/mc_1744618803268_img_009.png\n画像 10: /uploads/images/mc_1744618803268_img_010.png\n画像 11: /uploads/images/mc_1744618803268_img_011.png\n画像 12: /uploads/images/mc_1744618803268_img_012.png\n画像 13: /uploads/images/mc_1744618803268_img_013.png\n画像 14: /uploads/images/mc_1744618803268_img_014.png\n画像 15: /uploads/images/mc_1744618803268_img_015.png\n画像 16: /uploads/images/mc_1744618803268_img_016.png\n画像 17: /uploads/images/mc_1744618803268_img_017.png\n画像 18: /uploads/images/mc_1744618803268_img_018.png\n画像 19: /uploads/images/mc_1744618803268_img_019.png\n画像 20: /uploads/images/mc_1744618803268_img_020.png\n画像 21: /uploads/images/mc_1744618803268_img_021.png\n画像 22: /uploads/images/mc_1744618803268_img_022.png\n画像 23: /uploads/images/mc_1744618803268_img_023.png\n画像 24: /uploads/images/mc_1744618803268_img_024.png\n画像 25: /uploads/images/mc_1744618803268_img_025.png\n画像 26: /uploads/images/mc_1744618803268_img_026.png\n画像 27: /uploads/images/mc_1744618803268_img_027.png\n画像 28: /uploads/images/mc_1744618803268_img_028.png\n画像 29: /uploads/images/mc_1744618803268_img_029.png\n画像 30: /uploads/images/mc_1744618803268_img_030.png\n画像 31: /uploads/images/mc_1744618803268_img_031.png\n画像 32: /uploads/images/mc_1744618803268_img_032.png\n"
}